<?xml version="1.0" ?>
<?xml-stylesheet type='text/xsl' href='../resources/feed.xsl'?>
<interface xmlns="http://zero-install.sourceforge.net/2004/injector/interface" uri="https://apps.0install.net/devel/influxdb-client.xml">
  <name>InfluxDB Client</name>
  <summary>command line interface to interact with InfluxDB</summary>
  <description>The influx command line interface (CLI) includes commands to manage many aspects of InfluxDB, including buckets, organizations, users, tasks, etc.</description>
  <homepage>https://docs.influxdata.com/influxdb/v2.0/reference/cli/influx/</homepage>
  <icon href="https://raw.githubusercontent.com/0install/apps/master/devel/influxdb.png" type="image/png"/>
  <needs-terminal/>

  <entry-point binary-name="influx" command="run"/>

  <group license="MIT License">
    <implementation arch="Linux-x86_64" id="sha1new=a4c9465ae1f3fda33c35f869a5ec3defbc9c309f" main="influx" released="2020-11-10" stability="stable" version="2.0.0">
      <manifest-digest sha256new="Z2WB45FC7ZIF4363APWLRUF5VLOKN23DG7NWR3IHV4Y7YCJCBXCQ"/>
      <archive extract="influxdb_client_2.0.0_linux_amd64" href="https://dl.influxdata.com/influxdb/releases/influxdb_client_2.0.0_linux_amd64.tar.gz" size="11811171" type="application/x-compressed-tar"/>
    </implementation>
    <implementation arch="Darwin-x86_64" id="sha1new=e9ada667aa9929faaa8a2781c0d9d9098ee12b76" main="influx" released="2020-11-10" stability="stable" version="2.0.0">
      <manifest-digest sha256new="FC4CMZ4Q27ETKEFHNQSUN6ZJBVYHLFN54MQKQYMTD725AHVG52AQ"/>
      <archive extract="influxdb_client_2.0.0_darwin_amd64" href="https://dl.influxdata.com/influxdb/releases/influxdb_client_2.0.0_darwin_amd64.tar.gz" size="13073545" type="application/x-compressed-tar"/>
    </implementation>
    <implementation arch="Linux-x86_64" id="sha1new=3b9a12d018714d86ba8358ce63741bbd73d52b4f" main="influx" released="2020-11-11" stability="stable" version="2.0.1">
      <manifest-digest sha256new="2RQK5MWQZJD6AEQJYIEFMOAUMS5LGLEYTLLJRTEEQNKAYH7TPICA"/>
      <archive extract="influxdb_client_2.0.1_linux_amd64" href="https://dl.influxdata.com/influxdb/releases/influxdb_client_2.0.1_linux_amd64.tar.gz" size="11811160" type="application/x-compressed-tar"/>
    </implementation>
    <implementation arch="Darwin-x86_64" id="sha1new=c9991a747b6a16b4d5e984ead3e881f0fb7442b4" main="influx" released="2020-11-11" stability="stable" version="2.0.1">
      <manifest-digest sha256new="UMXHVVW3AE7GWFUA7YNZEZIF4XM3DDVYLFCADJXJ2NFINNTF3BYQ"/>
      <archive extract="influxdb_client_2.0.1_darwin_amd64" href="https://dl.influxdata.com/influxdb/releases/influxdb_client_2.0.1_darwin_amd64.tar.gz" size="13073544" type="application/x-compressed-tar"/>
    </implementation>
    <implementation arch="Linux-x86_64" id="sha1new=9c0621011ae76bcc0ec5d17cd3a649a59c7566c9" main="influx" released="2020-11-19" stability="stable" version="2.0.2">
      <manifest-digest sha256new="2WAUSWJG5GRTDK6PIUNAUGZDZ7MIQCRDJ6UKQRTSODY6UFEFLZFA"/>
      <archive extract="influxdb_client_2.0.2_linux_amd64" href="https://dl.influxdata.com/influxdb/releases/influxdb_client_2.0.2_linux_amd64.tar.gz" size="11894791" type="application/x-compressed-tar"/>
    </implementation>
    <implementation arch="Darwin-x86_64" id="sha1new=36b4c6c2d157429a14d6153144932c307cffcfda" main="influx" released="2020-11-19" stability="stable" version="2.0.2">
      <manifest-digest sha256new="TDYG3F3LVTDV5BB5SZCFDDACORCMGE4GBPZ4L64IZ3QWAR4KHRJQ"/>
      <archive extract="influxdb_client_2.0.2_darwin_amd64" href="https://dl.influxdata.com/influxdb/releases/influxdb_client_2.0.2_darwin_amd64.tar.gz" size="13159345" type="application/x-compressed-tar"/>
    </implementation>
    <implementation arch="Linux-x86_64" id="sha1new=6fd779f842fda162ee318d003e372700ad81e294" main="influx" released="2020-12-15" stability="stable" version="2.0.3">
      <manifest-digest sha256new="U7ZYGQQIV6IDO22ONZ47324PFZVTCESS66IA5L5QTBLJMRUKZYUQ"/>
      <archive extract="influxdb2_client_2.0.3_linux_amd64" href="https://dl.influxdata.com/influxdb/releases/influxdb2_client_2.0.3_linux_amd64.tar.gz" size="11947299" type="application/x-compressed-tar"/>
    </implementation>
    <implementation arch="Linux-unknown" id="sha1new=e67f633707d58bb6fa8cacdeefd71391e65448a1" main="influx" released="2020-12-15" stability="stable" version="2.0.3">
      <manifest-digest sha256new="HSV7PEQE3ZCTTSB32NFZKPVLPB3AYLTBYBAEKALFAGNGN4J7GOXA"/>
      <archive extract="influxdb2_client_2.0.3_linux_arm64" href="https://dl.influxdata.com/influxdb/releases/influxdb2_client_2.0.3_linux_arm64.tar.gz" size="11020726" type="application/x-compressed-tar"/>
    </implementation>
    <implementation arch="Darwin-x86_64" id="sha1new=90d485f8dcb5b43a531f5128fc5682add3d0f72e" main="influx" released="2020-12-15" stability="stable" version="2.0.3">
      <manifest-digest sha256new="FIFVIS3QPFWCCE6NZUNTSBB67EJG3YVAK5TWSYVHC73MGUG2QZ4Q"/>
      <archive extract="influxdb2_client_2.0.3_darwin_amd64" href="https://dl.influxdata.com/influxdb/releases/influxdb2_client_2.0.3_darwin_amd64.tar.gz" size="13234590" type="application/x-compressed-tar"/>
    </implementation>
    <implementation arch="Linux-x86_64" id="sha1new=dc069f6148388533b30d0874960b94a315e24935" main="influx" released="2021-02-11" stability="stable" version="2.0.4">
      <manifest-digest sha256new="I7KT5LVPAC5YN2NPSOPH76KJM5DRTXLCINRLQDSC76H7GLLA6YGQ"/>
      <archive extract="influxdb2-client-2.0.4-linux-amd64" href="https://dl.influxdata.com/influxdb/releases/influxdb2-client-2.0.4-linux-amd64.tar.gz" size="11892773" type="application/x-compressed-tar"/>
    </implementation>
    <implementation arch="Linux-aarch64" id="sha1new=863905605656c93565119143d39ecfea0e6fdac8" main="influx" released="2021-02-11" stability="stable" version="2.0.4">
      <manifest-digest sha256new="E2STTQDEOOJ7VYXSOPNJS4MX2ZLSNKB5OSVSU6P2U5MVFJMGJU6A"/>
      <archive extract="influxdb2-client-2.0.4-linux-arm64" href="https://dl.influxdata.com/influxdb/releases/influxdb2-client-2.0.4-linux-arm64.tar.gz" size="10972028" type="application/x-compressed-tar"/>
    </implementation>
    <implementation arch="Darwin-x86_64" id="sha1new=b1466b1ae0bc7f801454e61af0d649a08b7cf4f2" main="influx" released="2021-02-11" stability="stable" version="2.0.4">
      <manifest-digest sha256new="XFADF2XCSAHWMWZLMDWNASO7BCAWK4Z5VHZTK6UB54SBEIZ2W5QQ"/>
      <archive extract="influxdb2-client-2.0.4-darwin-amd64" href="https://dl.influxdata.com/influxdb/releases/influxdb2-client-2.0.4-darwin-amd64.tar.gz" size="13188303" type="application/x-compressed-tar"/>
    </implementation>
    <implementation arch="Linux-x86_64" main="influx" released="2021-04-27" stability="stable" version="2.0.5" id="sha1new=8c6e4431a5febc0031e9d79f03c62b8975a1147a">
      <manifest-digest sha256new="CXYG66WZL3VZF3QJNDELEHRR6AH3L5XBRPLQQ57JWBOB3U4IBX7A"/>
      <archive extract="influxdb2-client-2.0.5-linux-amd64" href="https://dl.influxdata.com/influxdb/releases/influxdb2-client-2.0.5-linux-amd64.tar.gz" type="application/x-compressed-tar" size="11758009"/>
    </implementation>
    <implementation arch="Linux-aarch64" main="influx" released="2021-04-27" stability="stable" version="2.0.5" id="sha1new=92383fe43c7e84664ec7503139ac5d0c447fddc7">
      <manifest-digest sha256new="ANDJ2O5QZRKBYLGSSSJQBGD2DGMBEHEKSGISEYMKTFH7BUZQMSJA"/>
      <archive extract="influxdb2-client-2.0.5-linux-arm64" href="https://dl.influxdata.com/influxdb/releases/influxdb2-client-2.0.5-linux-arm64.tar.gz" type="application/x-compressed-tar" size="12572446"/>
    </implementation>
    <implementation arch="Darwin-x86_64" main="influx" released="2021-04-27" stability="stable" version="2.0.5" id="sha1new=4f2c1c472b9cb1421c7baf5f66ee3c631ed8ef96">
      <manifest-digest sha256new="7NZKPMJCFPCSH3UUWUOWWRF3TO4QI6UZYDANJK7GR76D47NXX53A"/>
      <archive extract="influxdb2-client-2.0.5-darwin-amd64" href="https://dl.influxdata.com/influxdb/releases/influxdb2-client-2.0.5-darwin-amd64.tar.gz" type="application/x-compressed-tar" size="13119335"/>
    </implementation>
    <implementation arch="Linux-x86_64" main="influx" released="2021-04-29" stability="stable" version="2.0.6" id="sha1new=4b50c1839881fc10cc5df5eed3c8c84eea768d1f">
      <manifest-digest sha256new="EVGT4PCKOXVJLN22YPMFRLQPN5ANSO3BNONSEPYJIZRSNGOGBP3Q"/>
      <archive extract="influxdb2-client-2.0.6-linux-amd64" href="https://dl.influxdata.com/influxdb/releases/influxdb2-client-2.0.6-linux-amd64.tar.gz" type="application/x-compressed-tar" size="11758006"/>
    </implementation>
    <implementation arch="Linux-aarch64" main="influx" released="2021-04-29" stability="stable" version="2.0.6" id="sha1new=d3130128c493223c50be78467d6f6c85ec9304c2">
      <manifest-digest sha256new="CNQNMRWEZSI2HAF3IWGGWHRKYLA6NBBRXANYKRNBWBT3JLEWNO6A"/>
      <archive extract="influxdb2-client-2.0.6-linux-arm64" href="https://dl.influxdata.com/influxdb/releases/influxdb2-client-2.0.6-linux-arm64.tar.gz" type="application/x-compressed-tar" size="12572448"/>
    </implementation>
    <implementation arch="Darwin-x86_64" main="influx" released="2021-04-29" stability="stable" version="2.0.6" id="sha1new=034c2ec4695b60c301572dd4b49f81d526795af3">
      <manifest-digest sha256new="UJNQI3PT3UMCI7BZHTHXXUJ7V2ZD2APSPIGITBIXKOOPMUPOYS2A"/>
      <archive extract="influxdb2-client-2.0.6-darwin-amd64" href="https://dl.influxdata.com/influxdb/releases/influxdb2-client-2.0.6-darwin-amd64.tar.gz" type="application/x-compressed-tar" size="13119331"/>
    </implementation>
    <implementation arch="Linux-x86_64" main="influx" released="2021-06-04" stability="stable" version="2.0.7" id="sha1new=57acc6c04ff223504208698749108f20cea9124e">
      <manifest-digest sha256new="Y5RSSEEOINX5DWN3SCU5DGH7NBE3BSATUWEA4LR4SLPPHJPULVPQ"/>
      <archive extract="influxdb2-client-2.0.7-linux-amd64" href="https://dl.influxdata.com/influxdb/releases/influxdb2-client-2.0.7-linux-amd64.tar.gz" type="application/x-compressed-tar" size="11705919"/>
    </implementation>
    <implementation arch="Linux-aarch64" main="influx" released="2021-06-04" stability="stable" version="2.0.7" id="sha1new=08307f69696f52d01b78ac1b1c58fbde0c6b7ee3">
      <manifest-digest sha256new="LDQXD27CBSUKE3A7YT2P3NGHIQKCZDK5PQTAMUK75SZQLTWNB2UQ"/>
      <archive extract="influxdb2-client-2.0.7-linux-arm64" href="https://dl.influxdata.com/influxdb/releases/influxdb2-client-2.0.7-linux-arm64.tar.gz" type="application/x-compressed-tar" size="12512803"/>
    </implementation>
    <implementation arch="Darwin-x86_64" main="influx" released="2021-06-04" stability="stable" version="2.0.7" id="sha1new=56c6f1413279e073d45e52e2f4af515137e7b569">
      <manifest-digest sha256new="5FXLP5MXHGGNUR2AWSHCE5AMGOAQS5Q3H32QLNKG3EIIMZMIDKWQ"/>
      <archive extract="influxdb2-client-2.0.7-darwin-amd64" href="https://dl.influxdata.com/influxdb/releases/influxdb2-client-2.0.7-darwin-amd64.tar.gz" type="application/x-compressed-tar" size="13069756"/>
    </implementation>
    <implementation arch="Linux-x86_64" main="influx" released="2021-08-13" stability="stable" version="2.0.8" id="sha1new=15fc27c7ddfaea242241746c7de26aeaf12f705d">
      <manifest-digest sha256new="YZEW7OI4OZLPJKVK63KD2P33KIW2OWO5XQWCLJHAKZJ4UJJHDT6A"/>
      <archive extract="influxdb2-client-2.0.8-linux-amd64" href="https://dl.influxdata.com/influxdb/releases/influxdb2-client-2.0.8-linux-amd64.tar.gz" type="application/x-compressed-tar" size="10845222"/>
    </implementation>
    <implementation arch="Linux-aarch64" main="influx" released="2021-08-13" stability="stable" version="2.0.8" id="sha1new=509de69b4f02d8861666d63d6eb57849f407c79e">
      <manifest-digest sha256new="OUBPHZ2FAHNGS5RDVLWXRG3Z4JI43UK3HHVXSYCN6IBMFKLGJZNA"/>
      <archive extract="influxdb2-client-2.0.8-linux-arm64" href="https://dl.influxdata.com/influxdb/releases/influxdb2-client-2.0.8-linux-arm64.tar.gz" type="application/x-compressed-tar" size="11391887"/>
    </implementation>
    <implementation arch="Darwin-x86_64" main="influx" released="2021-08-13" stability="stable" version="2.0.8" id="sha1new=6e087989e48cdb049ac771fbad82f865475aa5e4">
      <manifest-digest sha256new="C752MYDMTWXDP7QVIN6RAUXCSUZSSZ6GEFHAEQ2CCGGVEVXLK45A"/>
      <archive extract="influxdb2-client-2.0.8-darwin-amd64" href="https://dl.influxdata.com/influxdb/releases/influxdb2-client-2.0.8-darwin-amd64.tar.gz" type="application/x-compressed-tar" size="12137587"/>
    </implementation>
    <implementation arch="Linux-x86_64" main="influx" released="2021-10-04" stability="stable" version="2.0.9" id="sha1new=cee832b647dd5878ec26843da81c4c6ccc9ba3f5">
      <manifest-digest sha256new="CNUMLDWWGRKUBT37ZT6IPTMRER6ZYWHQYXHO5SFUYPBHP3HYPEOA"/>
      <archive extract="influxdb2-client-2.0.9-linux-amd64" href="https://dl.influxdata.com/influxdb/releases/influxdb2-client-2.0.9-linux-amd64.tar.gz" type="application/x-compressed-tar" size="10659545"/>
    </implementation>
    <implementation arch="Linux-aarch64" main="influx" released="2021-10-04" stability="stable" version="2.0.9" id="sha1new=b1992157b2a83c39bcba0b7a98d5f5ae2d986104">
      <manifest-digest sha256new="UVCDYKB3IHKVQGL4575F4YAS5CE3FQ6PZZUGJCVGSURG6GPVBL2A"/>
      <archive extract="influxdb2-client-2.0.9-linux-arm64" href="https://dl.influxdata.com/influxdb/releases/influxdb2-client-2.0.9-linux-arm64.tar.gz" type="application/x-compressed-tar" size="11391931"/>
    </implementation>
    <implementation arch="Darwin-x86_64" main="influx" released="2021-10-04" stability="stable" version="2.0.9" id="sha1new=90acfcf08100b399cac536cbd399889d22b9f685">
      <manifest-digest sha256new="CBQWYKZLPGECH4NAYPP47MZEF7NZ3HDUQDPTR34RJHXAOVTAGWIQ"/>
      <archive extract="influxdb2-client-2.0.9-darwin-amd64" href="https://dl.influxdata.com/influxdb/releases/influxdb2-client-2.0.9-darwin-amd64.tar.gz" type="application/x-compressed-tar" size="11973199"/>
    </implementation>
  </group>
</interface>
<!-- Base64 Signature
iQEzBAABCgAdFiEEiMih83WShpHXNlwCWao5J8JOTh4FAmFcBAUACgkQWao5J8JOTh6ZJgf7B0kx
poXlPhekA38rJo7Ft8MBwXTQg+LPL0RpwnpT2XlkbjWkLB4/U8jqXjCg+uG0stW/TtQQ5xGmyXOl
DdW33HTdkmoFhkFt540vLV8sgpXO3ZlYddi8oLMb/WIUOr0ItjQ3sl2NCbjipxyw6MfreIkBBh8m
gTUmobRyNvlBgqvrni0wyW27rmcqKHb5PwJ074ipl/l0yjXUQQArs/ByaeckNI3MsilOnvNkxMFI
0aWYvY0IHf/67n1D4Ftz9SQEOtH/gil4wcMBv7bnOk05Z2RcM/hMrtV2fsSQGmqQy5u2XBxXV3EF
Z59UPHMUmNDAzImO31iRaj1x3l3TBdiJxA==

-->
